<?xml version="1.0" encoding="utf-8"?>
<helpItems schema="maml" xmlns="http://msh">
  <command:command xmlns:maml="http://schemas.microsoft.com/maml/2004/10" xmlns:command="http://schemas.microsoft.com/maml/dev/command/2004/10" xmlns:dev="http://schemas.microsoft.com/maml/dev/2004/10" xmlns:MSHelp="http://msdn.microsoft.com/mshelp">
    <command:details>
      <command:name>Add-Border</command:name>
      <command:verb>Add</command:verb>
      <command:noun>Border</command:noun>
      <maml:description>
        <maml:para>Create a text border around a string.</maml:para>
      </maml:description>
    </command:details>
    <maml:description>
      <maml:para>This command will create a character or text based border around a line of text. You might use this to create a formatted text report or to improve the display of information to the screen.</maml:para>
    </maml:description>
    <command:syntax>
      <command:syntaxItem>
        <maml:name>Add-Border</maml:name>
        <command:parameter required="true" variableLength="true" globbing="false" pipelineInput="True (ByValue)" position="1" aliases="none">
          <maml:name>Text</maml:name>
          <maml:Description>
            <maml:para>A single line of text that will be wrapped in a border.</maml:para>
          </maml:Description>
          <command:parameterValue required="true" variableLength="false">String</command:parameterValue>
          <dev:type>
            <maml:name>String</maml:name>
            <maml:uri />
          </dev:type>
          <dev:defaultValue>None</dev:defaultValue>
        </command:parameter>
        <command:parameter required="false" variableLength="true" globbing="false" pipelineInput="False" position="named" aliases="none">
          <maml:name>Character</maml:name>
          <maml:Description>
            <maml:para>The character to use for the border. It must be a single character.</maml:para>
          </maml:Description>
          <command:parameterValue required="true" variableLength="false">String</command:parameterValue>
          <dev:type>
            <maml:name>String</maml:name>
            <maml:uri />
          </dev:type>
          <dev:defaultValue>*</dev:defaultValue>
        </command:parameter>
        <command:parameter required="false" variableLength="true" globbing="false" pipelineInput="False" position="named" aliases="none">
          <maml:name>InsertBlanks</maml:name>
          <maml:Description>
            <maml:para>Insert blank lines before and after the text. The default behavior is to create a border box close to the text. See examples.</maml:para>
          </maml:Description>
          <dev:type>
            <maml:name>SwitchParameter</maml:name>
            <maml:uri />
          </dev:type>
          <dev:defaultValue>False</dev:defaultValue>
        </command:parameter>
        <command:parameter required="false" variableLength="true" globbing="false" pipelineInput="False" position="named" aliases="none">
          <maml:name>Tab</maml:name>
          <maml:Description>
            <maml:para>insert X number of tabs</maml:para>
          </maml:Description>
          <command:parameterValue required="true" variableLength="false">Int32</command:parameterValue>
          <dev:type>
            <maml:name>Int32</maml:name>
            <maml:uri />
          </dev:type>
          <dev:defaultValue>0</dev:defaultValue>
        </command:parameter>
      </command:syntaxItem>
      <command:syntaxItem>
        <maml:name>Add-Border</maml:name>
        <command:parameter required="true" variableLength="true" globbing="false" pipelineInput="False" position="1" aliases="none">
          <maml:name>TextBlock</maml:name>
          <maml:Description>
            <maml:para>A multiline block of text. You might want to trim blank lines from the beginning, end or both.</maml:para>
          </maml:Description>
          <command:parameterValue required="true" variableLength="false">String[]</command:parameterValue>
          <dev:type>
            <maml:name>String[]</maml:name>
            <maml:uri />
          </dev:type>
          <dev:defaultValue>None</dev:defaultValue>
        </command:parameter>
        <command:parameter required="false" variableLength="true" globbing="false" pipelineInput="False" position="named" aliases="none">
          <maml:name>Character</maml:name>
          <maml:Description>
            <maml:para>The character to use for the border. It must be a single character.</maml:para>
          </maml:Description>
          <command:parameterValue required="true" variableLength="false">String</command:parameterValue>
          <dev:type>
            <maml:name>String</maml:name>
            <maml:uri />
          </dev:type>
          <dev:defaultValue>*</dev:defaultValue>
        </command:parameter>
        <command:parameter required="false" variableLength="true" globbing="false" pipelineInput="False" position="named" aliases="none">
          <maml:name>InsertBlanks</maml:name>
          <maml:Description>
            <maml:para>Insert blank lines before and after the text. The default behavior is to create a border box close to the text. See examples.</maml:para>
          </maml:Description>
          <dev:type>
            <maml:name>SwitchParameter</maml:name>
            <maml:uri />
          </dev:type>
          <dev:defaultValue>False</dev:defaultValue>
        </command:parameter>
        <command:parameter required="false" variableLength="true" globbing="false" pipelineInput="False" position="named" aliases="none">
          <maml:name>Tab</maml:name>
          <maml:Description>
            <maml:para>insert X number of tabs</maml:para>
          </maml:Description>
          <command:parameterValue required="true" variableLength="false">Int32</command:parameterValue>
          <dev:type>
            <maml:name>Int32</maml:name>
            <maml:uri />
          </dev:type>
          <dev:defaultValue>0</dev:defaultValue>
        </command:parameter>
      </command:syntaxItem>
    </command:syntax>
    <command:parameters>
      <command:parameter required="false" variableLength="true" globbing="false" pipelineInput="False" position="named" aliases="none">
        <maml:name>Character</maml:name>
        <maml:Description>
          <maml:para>The character to use for the border. It must be a single character.</maml:para>
        </maml:Description>
        <command:parameterValue required="true" variableLength="false">String</command:parameterValue>
        <dev:type>
          <maml:name>String</maml:name>
          <maml:uri />
        </dev:type>
        <dev:defaultValue>*</dev:defaultValue>
      </command:parameter>
      <command:parameter required="false" variableLength="true" globbing="false" pipelineInput="False" position="named" aliases="none">
        <maml:name>InsertBlanks</maml:name>
        <maml:Description>
          <maml:para>Insert blank lines before and after the text. The default behavior is to create a border box close to the text. See examples.</maml:para>
        </maml:Description>
        <command:parameterValue required="false" variableLength="false">SwitchParameter</command:parameterValue>
        <dev:type>
          <maml:name>SwitchParameter</maml:name>
          <maml:uri />
        </dev:type>
        <dev:defaultValue>False</dev:defaultValue>
      </command:parameter>
      <command:parameter required="false" variableLength="true" globbing="false" pipelineInput="False" position="named" aliases="none">
        <maml:name>Tab</maml:name>
        <maml:Description>
          <maml:para>insert X number of tabs</maml:para>
        </maml:Description>
        <command:parameterValue required="true" variableLength="false">Int32</command:parameterValue>
        <dev:type>
          <maml:name>Int32</maml:name>
          <maml:uri />
        </dev:type>
        <dev:defaultValue>0</dev:defaultValue>
      </command:parameter>
      <command:parameter required="true" variableLength="true" globbing="false" pipelineInput="True (ByValue)" position="1" aliases="none">
        <maml:name>Text</maml:name>
        <maml:Description>
          <maml:para>A single line of text that will be wrapped in a border.</maml:para>
        </maml:Description>
        <command:parameterValue required="true" variableLength="false">String</command:parameterValue>
        <dev:type>
          <maml:name>String</maml:name>
          <maml:uri />
        </dev:type>
        <dev:defaultValue>None</dev:defaultValue>
      </command:parameter>
      <command:parameter required="true" variableLength="true" globbing="false" pipelineInput="False" position="1" aliases="none">
        <maml:name>TextBlock</maml:name>
        <maml:Description>
          <maml:para>A multiline block of text. You might want to trim blank lines from the beginning, end or both.</maml:para>
        </maml:Description>
        <command:parameterValue required="true" variableLength="false">String[]</command:parameterValue>
        <dev:type>
          <maml:name>String[]</maml:name>
          <maml:uri />
        </dev:type>
        <dev:defaultValue>None</dev:defaultValue>
      </command:parameter>
    </command:parameters>
    <command:inputTypes>
      <command:inputType>
        <dev:type>
          <maml:name>None</maml:name>
        </dev:type>
        <maml:description>
          <maml:para></maml:para>
        </maml:description>
      </command:inputType>
    </command:inputTypes>
    <command:returnValues>
      <command:returnValue>
        <dev:type>
          <maml:name>System.String</maml:name>
        </dev:type>
        <maml:description>
          <maml:para></maml:para>
        </maml:description>
      </command:returnValue>
    </command:returnValues>
    <maml:alertSet>
      <maml:alert>
        <maml:para>Learn more about PowerShell: http://jdhitsolutions.com/blog/essential-powershell-resources/</maml:para>
      </maml:alert>
    </maml:alertSet>
    <command:examples>
      <command:example>
        <maml:title>Example 1</maml:title>
        <dev:code>PS C:\&gt; add-border "PowerShell Wins!"

********************
* PowerShell Wins! *
********************</dev:code>
        <dev:remarks>
          <maml:para></maml:para>
        </dev:remarks>
      </command:example>
      <command:example>
        <maml:title>Example 2</maml:title>
        <dev:code>PS C:\&gt; add-border "PowerShell Wins!" -tab 1

     ********************
     * PowerShell Wins! *
     ********************</dev:code>
        <dev:remarks>
          <maml:para>Note that this example may not format properly in the console.</maml:para>
        </dev:remarks>
      </command:example>
      <command:example>
        <maml:title>Example 3</maml:title>
        <dev:code>PS C:\&gt; add-border "PowerShell Wins!" -character "-" -insertBlanks

--------------------
-                  -
- PowerShell Wins! -
-                  -
--------------------</dev:code>
        <dev:remarks>
          <maml:para></maml:para>
        </dev:remarks>
      </command:example>
      <command:example>
        <maml:title>Example 4</maml:title>
        <dev:code>PS C:\&gt; add-border -textblock (get-service win* | out-string).trim()

**********************************************************************
* Status   Name               DisplayName                            *
* ------   ----               -----------                            *
* Stopped  WinDefend          Windows Defender Antivirus Service     *
* Running  WinHttpAutoProx... WinHTTP Web Proxy Auto-Discovery Se... *
* Running  Winmgmt            Windows Management Instrumentation     *
* Stopped  WinRM              Windows Remote Management (WS-Manag... *
**********************************************************************</dev:code>
        <dev:remarks>
          <maml:para>Create a border around the output of a Get-Service command.</maml:para>
        </dev:remarks>
      </command:example>
    </command:examples>
    <command:relatedLinks />
  </command:command>
  <command:command xmlns:maml="http://schemas.microsoft.com/maml/2004/10" xmlns:command="http://schemas.microsoft.com/maml/dev/command/2004/10" xmlns:dev="http://schemas.microsoft.com/maml/dev/2004/10" xmlns:MSHelp="http://msdn.microsoft.com/mshelp">
    <command:details>
      <command:name>Get-PSWho</command:name>
      <command:verb>Get</command:verb>
      <command:noun>PSWho</command:noun>
      <maml:description>
        <maml:para>Get PowerShell user summary information</maml:para>
      </maml:description>
    </command:details>
    <maml:description>
      <maml:para>This command will provide a summary of relevant information for the current  user in a PowerShell session. You might use this to troubleshoot an end-user problem running a script or command.</maml:para>
      <maml:para>The default behavior is to write an object to the pipeline, but you can use the -AsString parameter to force the command to write a string. This makes it easier to use in your scripts with Write-Verbose.</maml:para>
    </maml:description>
    <command:syntax>
      <command:syntaxItem>
        <maml:name>Get-PSWho</maml:name>
        <command:parameter required="false" variableLength="true" globbing="false" pipelineInput="False" position="named" aliases="none">
          <maml:name>AsString</maml:name>
          <maml:Description>
            <maml:para>Write the summary object as a string.</maml:para>
          </maml:Description>
          <dev:type>
            <maml:name>SwitchParameter</maml:name>
            <maml:uri />
          </dev:type>
          <dev:defaultValue>False</dev:defaultValue>
        </command:parameter>
      </command:syntaxItem>
    </command:syntax>
    <command:parameters>
      <command:parameter required="false" variableLength="true" globbing="false" pipelineInput="False" position="named" aliases="none">
        <maml:name>AsString</maml:name>
        <maml:Description>
          <maml:para>Write the summary object as a string.</maml:para>
        </maml:Description>
        <command:parameterValue required="false" variableLength="false">SwitchParameter</command:parameterValue>
        <dev:type>
          <maml:name>SwitchParameter</maml:name>
          <maml:uri />
        </dev:type>
        <dev:defaultValue>False</dev:defaultValue>
      </command:parameter>
    </command:parameters>
    <command:inputTypes>
      <command:inputType>
        <dev:type>
          <maml:name>none</maml:name>
        </dev:type>
        <maml:description>
          <maml:para></maml:para>
        </maml:description>
      </command:inputType>
    </command:inputTypes>
    <command:returnValues>
      <command:returnValue>
        <dev:type>
          <maml:name>[pscustomobject]</maml:name>
        </dev:type>
        <maml:description>
          <maml:para></maml:para>
        </maml:description>
      </command:returnValue>
      <command:returnValue>
        <dev:type>
          <maml:name>[system.string]</maml:name>
        </dev:type>
        <maml:description>
          <maml:para></maml:para>
        </maml:description>
      </command:returnValue>
    </command:returnValues>
    <maml:alertSet>
      <maml:alert>
        <maml:para>Learn more about PowerShell: http://jdhitsolutions.com/blog/essential-powershell-resources/</maml:para>
      </maml:alert>
    </maml:alertSet>
    <command:examples>
      <command:example>
        <maml:title>Example 1</maml:title>
        <dev:code>PS C:\&gt; Get-PSWho

User            : BOVINE320\Jeff
Elevated        : True
Computername    : BOVINE320
OperatingSystem : Microsoft Windows 10 Pro \[64-bit\]
OSVersion       : 10.0.16299
PSVersion       : 5.1.16299.64
Edition         : Desktop
PSHost          : ConsoleHost
WSMan           : 3.0
ExecutionPolicy : RemoteSigned
Culture         : en-US</dev:code>
        <dev:remarks>
          <maml:para></maml:para>
        </dev:remarks>
      </command:example>
      <command:example>
        <maml:title>Example 2</maml:title>
        <dev:code>PS /home/jhicks&gt; Get-PSWho

User            : jhicks
Elevated        : NA
Computername    : Bovine320
OperatingSystem : Linux 4.4.0-43-Microsoft #1-Microsoft Wed Dec 31 14:42:53 PST 2014
OSVersion       : Ubuntu 16.04.3 LTS
PSVersion       : 6.0.0-rc
Edition         : Core
PSHost          : ConsoleHost
WSMan           : 3.0
ExecutionPolicy : Unrestricted
Culture         : en-US</dev:code>
        <dev:remarks>
          <maml:para></maml:para>
        </dev:remarks>
      </command:example>
      <command:example>
        <maml:title>Example 3</maml:title>
        <dev:code>PS C:\&gt; Get-PSWho

User            : BOVINE320\Jeff
Elevated        : True
Computername    : BOVINE320
OperatingSystem : Microsoft Windows 10 Pro \[64-bit\]
OSVersion       : 10.0.16299
PSVersion       : 6.0.0-rc
Edition         : Core
PSHost          : ConsoleHost
WSMan           : 3.0
ExecutionPolicy : RemoteSigned
Culture         : en-US</dev:code>
        <dev:remarks>
          <maml:para></maml:para>
        </dev:remarks>
      </command:example>
      <command:example>
        <maml:title>Example 4</maml:title>
        <dev:code>PS C:\&gt; Get-PSWho -asString | Set-Content c:\test\who.txt</dev:code>
        <dev:remarks>
          <maml:para></maml:para>
        </dev:remarks>
      </command:example>
    </command:examples>
    <command:relatedLinks>
      <maml:navigationLink>
        <maml:linkText>Get-CimInstance</maml:linkText>
        <maml:uri></maml:uri>
      </maml:navigationLink>
      <maml:navigationLink>
        <maml:linkText>Get-ExecutionPolicy</maml:linkText>
        <maml:uri></maml:uri>
      </maml:navigationLink>
      <maml:navigationLink>
        <maml:linkText>$PSVersionTable</maml:linkText>
        <maml:uri></maml:uri>
      </maml:navigationLink>
      <maml:navigationLink>
        <maml:linkText>$Host</maml:linkText>
        <maml:uri></maml:uri>
      </maml:navigationLink>
    </command:relatedLinks>
  </command:command>
  <command:command xmlns:maml="http://schemas.microsoft.com/maml/2004/10" xmlns:command="http://schemas.microsoft.com/maml/dev/command/2004/10" xmlns:dev="http://schemas.microsoft.com/maml/dev/2004/10" xmlns:MSHelp="http://msdn.microsoft.com/mshelp">
    <command:details>
      <command:name>New-CustomFileName</command:name>
      <command:verb>New</command:verb>
      <command:noun>CustomFileName</command:noun>
      <maml:description>
        <maml:para>Create a custom file name based on a template.</maml:para>
      </maml:description>
    </command:details>
    <maml:description>
      <maml:para>This command will generate a custom file name based on a template string that you provide. You can create a template string using any of these variables. Most of these should be self-explanatory</maml:para>
      <maml:para>
- %username
- %computername
- %year  - 4 digit year
- %yr  - 2 digit year
- %monthname - The abbreviated month name
- %month  - The month number
- %dayofweek - The full name of the week day
- %day
- %hour
- %minute
- %time  - A compact string of HourMinuteSecond
- %string - A random string
- %guid

You can also insert a random number using %### with a # character for each digit. If you want a 2 digit random number use %##. If you want 6 digits, use %######.</maml:para>
      <maml:para>The command will attempt to preserve case for any non pattern string, but you should separate it from other placeholder patterns with one of these characters: - ( ) [ ] or a . Using an underscore will not work.</maml:para>
      <maml:para>
      New-CustomFilename "%Year_LOG-%computername.txt"
2017_log-Bovine320.txt</maml:para>
      <maml:para>
      New-CustomFilename "%Year-LOG-%computername.txt"
2017-LOG-Bovine320.txt</maml:para>
      <maml:para>Another option, is to turn the entire name into upper or lower case.</maml:para>
      <maml:para>    
      New-CustomFilename "%Year%Monthname-LOG-%computername[%username].txt" -case lower
2017nov-log-bovine320[jeff].txt</maml:para>
      <maml:para>This command does not create the file, it only generates a name for you to use.</maml:para>
    </maml:description>
    <command:syntax>
      <command:syntaxItem>
        <maml:name>New-CustomFileName</maml:name>
        <command:parameter required="true" variableLength="true" globbing="false" pipelineInput="False" position="0" aliases="none">
          <maml:name>Template</maml:name>
          <maml:Description>
            <maml:para>A string that defines the naming pattern based on a set of placeholders.</maml:para>
          </maml:Description>
          <command:parameterValue required="true" variableLength="false">String</command:parameterValue>
          <dev:type>
            <maml:name>String</maml:name>
            <maml:uri />
          </dev:type>
          <dev:defaultValue>None</dev:defaultValue>
        </command:parameter>
        <command:parameter required="false" variableLength="true" globbing="false" pipelineInput="False" position="named" aliases="none">
          <maml:name>Case</maml:name>
          <maml:Description>
            <maml:para>Some values like username or computername might be in different case than what you want. You can use the default value, or return a value that is all upper or lower case.</maml:para>
          </maml:Description>
          <command:parameterValueGroup>
            <command:parameterValue required="false" command:variableLength="false">Lower</command:parameterValue>
            <command:parameterValue required="false" command:variableLength="false">Upper</command:parameterValue>
            <command:parameterValue required="false" command:variableLength="false">Default</command:parameterValue>
          </command:parameterValueGroup>
          <command:parameterValue required="true" variableLength="false">String</command:parameterValue>
          <dev:type>
            <maml:name>String</maml:name>
            <maml:uri />
          </dev:type>
          <dev:defaultValue>None</dev:defaultValue>
        </command:parameter>
      </command:syntaxItem>
    </command:syntax>
    <command:parameters>
      <command:parameter required="false" variableLength="true" globbing="false" pipelineInput="False" position="named" aliases="none">
        <maml:name>Case</maml:name>
        <maml:Description>
          <maml:para>Some values like username or computername might be in different case than what you want. You can use the default value, or return a value that is all upper or lower case.</maml:para>
        </maml:Description>
        <command:parameterValue required="true" variableLength="false">String</command:parameterValue>
        <dev:type>
          <maml:name>String</maml:name>
          <maml:uri />
        </dev:type>
        <dev:defaultValue>None</dev:defaultValue>
      </command:parameter>
      <command:parameter required="true" variableLength="true" globbing="false" pipelineInput="False" position="0" aliases="none">
        <maml:name>Template</maml:name>
        <maml:Description>
          <maml:para>A string that defines the naming pattern based on a set of placeholders.</maml:para>
        </maml:Description>
        <command:parameterValue required="true" variableLength="false">String</command:parameterValue>
        <dev:type>
          <maml:name>String</maml:name>
          <maml:uri />
        </dev:type>
        <dev:defaultValue>None</dev:defaultValue>
      </command:parameter>
    </command:parameters>
    <command:inputTypes>
      <command:inputType>
        <dev:type>
          <maml:name>None</maml:name>
        </dev:type>
        <maml:description>
          <maml:para></maml:para>
        </maml:description>
      </command:inputType>
    </command:inputTypes>
    <command:returnValues>
      <command:returnValue>
        <dev:type>
          <maml:name>System.String</maml:name>
        </dev:type>
        <maml:description>
          <maml:para></maml:para>
        </maml:description>
      </command:returnValue>
    </command:returnValues>
    <maml:alertSet>
      <maml:alert>
        <maml:para>Learn more about PowerShell: http://jdhitsolutions.com/blog/essential-powershell-resources/</maml:para>
      </maml:alert>
    </maml:alertSet>
    <command:examples>
      <command:example>
        <maml:title>Example 1</maml:title>
        <dev:code>PS C:\&gt; New-CustomFileName %computername_%day%monthname%yr-%time.log
COWPC_28Nov17-142138.log</dev:code>
        <dev:remarks>
          <maml:para></maml:para>
        </dev:remarks>
      </command:example>
      <command:example>
        <maml:title>Example 2</maml:title>
        <dev:code>PS C:\&gt; New-CustomFileName %dayofweek-%####.dat
Tuesday-3128.dat</dev:code>
        <dev:remarks>
          <maml:para>Create a custom file name using the day of the week and a 4 digit random number.</maml:para>
        </dev:remarks>
      </command:example>
      <command:example>
        <maml:title>Example 3</maml:title>
        <dev:code>PS C:\&gt; New-CustomFileName %username-%string.tmp -Case Upper
JEFF-Z0XUXMFS.TMP</dev:code>
        <dev:remarks>
          <maml:para>Create an upper case custom file name. The %string placeholder will be replaced with a random 8 character string.</maml:para>
        </dev:remarks>
      </command:example>
    </command:examples>
    <command:relatedLinks>
      <maml:navigationLink>
        <maml:linkText>New-RandomFileName</maml:linkText>
        <maml:uri></maml:uri>
      </maml:navigationLink>
    </command:relatedLinks>
  </command:command>
  <command:command xmlns:maml="http://schemas.microsoft.com/maml/2004/10" xmlns:command="http://schemas.microsoft.com/maml/dev/command/2004/10" xmlns:dev="http://schemas.microsoft.com/maml/dev/2004/10" xmlns:MSHelp="http://msdn.microsoft.com/mshelp">
    <command:details>
      <command:name>New-RandomFileName</command:name>
      <command:verb>New</command:verb>
      <command:noun>RandomFileName</command:noun>
      <maml:description>
        <maml:para>Create a random file name.</maml:para>
      </maml:description>
    </command:details>
    <maml:description>
      <maml:para>Create a new random file name. The default is a completely random name including the extension. But you can also create a filename that includes either the TEMP folder or the user's home folder. In the case of a Windows system, the home folder will be the documents folder.</maml:para>
      <maml:para>This command does not create the file, it only generates a name for you to use.</maml:para>
    </maml:description>
    <command:syntax>
      <command:syntaxItem>
        <maml:name>New-RandomFileName</maml:name>
        <command:parameter required="false" variableLength="true" globbing="false" pipelineInput="False" position="named" aliases="none">
          <maml:name>Extension</maml:name>
          <maml:Description>
            <maml:para>Use a specific extension. Do not include the period.</maml:para>
          </maml:Description>
          <command:parameterValue required="true" variableLength="false">String</command:parameterValue>
          <dev:type>
            <maml:name>String</maml:name>
            <maml:uri />
          </dev:type>
          <dev:defaultValue>None</dev:defaultValue>
        </command:parameter>
        <command:parameter required="false" variableLength="true" globbing="false" pipelineInput="False" position="named" aliases="home">
          <maml:name>UseHomeFolder</maml:name>
          <maml:Description>
            <maml:para>Include the user's HOME folder.</maml:para>
          </maml:Description>
          <dev:type>
            <maml:name>SwitchParameter</maml:name>
            <maml:uri />
          </dev:type>
          <dev:defaultValue>False</dev:defaultValue>
        </command:parameter>
      </command:syntaxItem>
      <command:syntaxItem>
        <maml:name>New-RandomFileName</maml:name>
        <command:parameter required="false" variableLength="true" globbing="false" pipelineInput="False" position="named" aliases="none">
          <maml:name>Extension</maml:name>
          <maml:Description>
            <maml:para>Use a specific extension. Do not include the period.</maml:para>
          </maml:Description>
          <command:parameterValue required="true" variableLength="false">String</command:parameterValue>
          <dev:type>
            <maml:name>String</maml:name>
            <maml:uri />
          </dev:type>
          <dev:defaultValue>None</dev:defaultValue>
        </command:parameter>
        <command:parameter required="false" variableLength="true" globbing="false" pipelineInput="False" position="named" aliases="temp">
          <maml:name>UseTempFolder</maml:name>
          <maml:Description>
            <maml:para>Include the TEMP folder.</maml:para>
          </maml:Description>
          <dev:type>
            <maml:name>SwitchParameter</maml:name>
            <maml:uri />
          </dev:type>
          <dev:defaultValue>False</dev:defaultValue>
        </command:parameter>
      </command:syntaxItem>
    </command:syntax>
    <command:parameters>
      <command:parameter required="false" variableLength="true" globbing="false" pipelineInput="False" position="named" aliases="none">
        <maml:name>Extension</maml:name>
        <maml:Description>
          <maml:para>Use a specific extension. Do not include the period.</maml:para>
        </maml:Description>
        <command:parameterValue required="true" variableLength="false">String</command:parameterValue>
        <dev:type>
          <maml:name>String</maml:name>
          <maml:uri />
        </dev:type>
        <dev:defaultValue>None</dev:defaultValue>
      </command:parameter>
      <command:parameter required="false" variableLength="true" globbing="false" pipelineInput="False" position="named" aliases="home">
        <maml:name>UseHomeFolder</maml:name>
        <maml:Description>
          <maml:para>Include the user's HOME folder.</maml:para>
        </maml:Description>
        <command:parameterValue required="false" variableLength="false">SwitchParameter</command:parameterValue>
        <dev:type>
          <maml:name>SwitchParameter</maml:name>
          <maml:uri />
        </dev:type>
        <dev:defaultValue>False</dev:defaultValue>
      </command:parameter>
      <command:parameter required="false" variableLength="true" globbing="false" pipelineInput="False" position="named" aliases="temp">
        <maml:name>UseTempFolder</maml:name>
        <maml:Description>
          <maml:para>Include the TEMP folder.</maml:para>
        </maml:Description>
        <command:parameterValue required="false" variableLength="false">SwitchParameter</command:parameterValue>
        <dev:type>
          <maml:name>SwitchParameter</maml:name>
          <maml:uri />
        </dev:type>
        <dev:defaultValue>False</dev:defaultValue>
      </command:parameter>
    </command:parameters>
    <command:inputTypes>
      <command:inputType>
        <dev:type>
          <maml:name>None</maml:name>
        </dev:type>
        <maml:description>
          <maml:para></maml:para>
        </maml:description>
      </command:inputType>
    </command:inputTypes>
    <command:returnValues>
      <command:returnValue>
        <dev:type>
          <maml:name>System.String</maml:name>
        </dev:type>
        <maml:description>
          <maml:para></maml:para>
        </maml:description>
      </command:returnValue>
    </command:returnValues>
    <maml:alertSet>
      <maml:alert>
        <maml:para>Learn more about PowerShell: http://jdhitsolutions.com/blog/essential-powershell-resources/</maml:para>
      </maml:alert>
    </maml:alertSet>
    <command:examples>
      <command:example>
        <maml:title>Example 1</maml:title>
        <dev:code>PS C:\&gt; new-randomfilename
fykxecvh.ipw</dev:code>
        <dev:remarks>
          <maml:para></maml:para>
        </dev:remarks>
      </command:example>
      <command:example>
        <maml:title>Example 2</maml:title>
        <dev:code>PS C:\&gt; new-randomfilename -extension dat
emevgq3r.dat</dev:code>
        <dev:remarks>
          <maml:para>Specify a file extension.</maml:para>
        </dev:remarks>
      </command:example>
      <command:example>
        <maml:title>Example 3</maml:title>
        <dev:code>PS C:\&gt; new-randomfilename -extension log -UseHomeFolder
C:\Users\Jeff\Documents\kbyw4fda.log</dev:code>
        <dev:remarks>
          <maml:para>Create a random file name using the user's home folder. In Windows this will be the Documents folder.</maml:para>
        </dev:remarks>
      </command:example>
      <command:example>
        <maml:title>Example 4</maml:title>
        <dev:code>PS /mnt/c/scripts&gt; new-randomfilename -home -Extension tmp
/home/jhicks/oces0epq.tmp</dev:code>
        <dev:remarks>
          <maml:para>Create a random file name using the user's home folder on a Linux installation.</maml:para>
        </dev:remarks>
      </command:example>
    </command:examples>
    <command:relatedLinks>
      <maml:navigationLink>
        <maml:linkText>New-CustomFileName</maml:linkText>
        <maml:uri></maml:uri>
      </maml:navigationLink>
    </command:relatedLinks>
  </command:command>
  <command:command xmlns:maml="http://schemas.microsoft.com/maml/2004/10" xmlns:command="http://schemas.microsoft.com/maml/dev/command/2004/10" xmlns:dev="http://schemas.microsoft.com/maml/dev/2004/10" xmlns:MSHelp="http://msdn.microsoft.com/mshelp">
    <command:details>
      <command:name>Out-ConditionalColor</command:name>
      <command:verb>Out</command:verb>
      <command:noun>ConditionalColor</command:noun>
      <maml:description>
        <maml:para>Display colorized pipelined output.</maml:para>
      </maml:description>
    </command:details>
    <maml:description>
      <maml:para>This command is designed to take pipeline input and display it in a colorized format, based on a set of conditions. Unlike Write-Host which doesn't write to the pipeline, this command will write to the pipeline. You can get colorized data and save the output to a variable at the same time, although you'll need to use the common OutVariable parameter (see examples).</maml:para>
      <maml:para>The default behavior is to use a hash table with a property name and color. The color must be one of the standard console colors used with Write-Host.</maml:para>
      <maml:para>    $c = @{Stopped='Red';Running='Green'}</maml:para>
      <maml:para>You can then pipe an expression to this command, specifying a property name and the hash table. If the property matches the key name, the output for that object will be colored using the corresponding hash table value.</maml:para>
      <maml:para>    get-service -diplayname windows* | out-conditionalcolor $c -property status </maml:para>
      <maml:para>Or you can do more complex processing with an ordered hash table constructed using this format:</maml:para>
      <maml:para>    [ordered]@{ &lt;comparison scriptblock&gt; = &lt;color&gt; }</maml:para>
      <maml:para>The comparison scriptblock can use $PSitem.</maml:para>
      <maml:para>    $h=[ordered]@{
        {$psitem.ws -gt 500mb}='red'
        {$psitem.ws -gt 300mb}='yellow'
        {$psitem.ws -gt 200mb}='cyan'
  }</maml:para>
      <maml:para>When doing a complex comparison you must use an [ordered] hashtable as each key will be processed in order using an If/ElseIf statement.</maml:para>
      <maml:para>This command should be the last part of any pipelined expression. If you pipe to anything else, such as Sort-Object, you will lose your color formatting. Do any other sorting or filtering before piping to this command.</maml:para>
      <maml:para>This command works best in the PowerShell console. It won't do anything in the PowerShell ISE.</maml:para>
      <maml:para>LIMITATIONS</maml:para>
      <maml:para>Due to the nature of PowerShell's formatting system there are some limitations with this command. If the first item in your output matches one of your conditions, any text before it, such as headers, will also be colorized. This command will have no affect if the incoming object does not have a defined format view. This means you can't pipe custom objects or something using Select-Object that only includes selected properties to this command.</maml:para>
    </maml:description>
    <command:syntax>
      <command:syntaxItem>
        <maml:name>Out-ConditionalColor</maml:name>
        <command:parameter required="true" variableLength="true" globbing="false" pipelineInput="False" position="0" aliases="none">
          <maml:name>Conditions</maml:name>
          <maml:Description>
            <maml:para>Use an ordered hashtable for more complex processing. See examples.</maml:para>
          </maml:Description>
          <command:parameterValue required="true" variableLength="false">OrderedDictionary</command:parameterValue>
          <dev:type>
            <maml:name>OrderedDictionary</maml:name>
            <maml:uri />
          </dev:type>
          <dev:defaultValue>None</dev:defaultValue>
        </command:parameter>
        <command:parameter required="true" variableLength="true" globbing="false" pipelineInput="True (ByValue)" position="named" aliases="none">
          <maml:name>InputObject</maml:name>
          <maml:Description>
            <maml:para>Output from a PowerShell expression that you want to colorize</maml:para>
          </maml:Description>
          <command:parameterValue required="true" variableLength="false">PSObject[]</command:parameterValue>
          <dev:type>
            <maml:name>PSObject[]</maml:name>
            <maml:uri />
          </dev:type>
          <dev:defaultValue>None</dev:defaultValue>
        </command:parameter>
      </command:syntaxItem>
      <command:syntaxItem>
        <maml:name>Out-ConditionalColor</maml:name>
        <command:parameter required="true" variableLength="true" globbing="false" pipelineInput="False" position="0" aliases="none">
          <maml:name>PropertyConditions</maml:name>
          <maml:Description>
            <maml:para>Use a simple hashtable for basic processing or an ordered hash table for complex.</maml:para>
          </maml:Description>
          <command:parameterValue required="true" variableLength="false">Hashtable</command:parameterValue>
          <dev:type>
            <maml:name>Hashtable</maml:name>
            <maml:uri />
          </dev:type>
          <dev:defaultValue>None</dev:defaultValue>
        </command:parameter>
        <command:parameter required="true" variableLength="true" globbing="false" pipelineInput="True (ByValue)" position="named" aliases="none">
          <maml:name>InputObject</maml:name>
          <maml:Description>
            <maml:para>Output from a PowerShell expression that you want to colorize</maml:para>
          </maml:Description>
          <command:parameterValue required="true" variableLength="false">PSObject[]</command:parameterValue>
          <dev:type>
            <maml:name>PSObject[]</maml:name>
            <maml:uri />
          </dev:type>
          <dev:defaultValue>None</dev:defaultValue>
        </command:parameter>
        <command:parameter required="true" variableLength="true" globbing="false" pipelineInput="False" position="named" aliases="none">
          <maml:name>Property</maml:name>
          <maml:Description>
            <maml:para>When using a simple hash table, specify the property to compare which will be done by using the -eq operator.</maml:para>
          </maml:Description>
          <command:parameterValue required="true" variableLength="false">String</command:parameterValue>
          <dev:type>
            <maml:name>String</maml:name>
            <maml:uri />
          </dev:type>
          <dev:defaultValue>None</dev:defaultValue>
        </command:parameter>
      </command:syntaxItem>
    </command:syntax>
    <command:parameters>
      <command:parameter required="true" variableLength="true" globbing="false" pipelineInput="False" position="0" aliases="none">
        <maml:name>Conditions</maml:name>
        <maml:Description>
          <maml:para>Use an ordered hashtable for more complex processing. See examples.</maml:para>
        </maml:Description>
        <command:parameterValue required="true" variableLength="false">OrderedDictionary</command:parameterValue>
        <dev:type>
          <maml:name>OrderedDictionary</maml:name>
          <maml:uri />
        </dev:type>
        <dev:defaultValue>None</dev:defaultValue>
      </command:parameter>
      <command:parameter required="true" variableLength="true" globbing="false" pipelineInput="True (ByValue)" position="named" aliases="none">
        <maml:name>InputObject</maml:name>
        <maml:Description>
          <maml:para>Output from a PowerShell expression that you want to colorize</maml:para>
        </maml:Description>
        <command:parameterValue required="true" variableLength="false">PSObject[]</command:parameterValue>
        <dev:type>
          <maml:name>PSObject[]</maml:name>
          <maml:uri />
        </dev:type>
        <dev:defaultValue>None</dev:defaultValue>
      </command:parameter>
      <command:parameter required="true" variableLength="true" globbing="false" pipelineInput="False" position="named" aliases="none">
        <maml:name>Property</maml:name>
        <maml:Description>
          <maml:para>When using a simple hash table, specify the property to compare which will be done by using the -eq operator.</maml:para>
        </maml:Description>
        <command:parameterValue required="true" variableLength="false">String</command:parameterValue>
        <dev:type>
          <maml:name>String</maml:name>
          <maml:uri />
        </dev:type>
        <dev:defaultValue>None</dev:defaultValue>
      </command:parameter>
      <command:parameter required="true" variableLength="true" globbing="false" pipelineInput="False" position="0" aliases="none">
        <maml:name>PropertyConditions</maml:name>
        <maml:Description>
          <maml:para>Use a simple hashtable for basic processing or an ordered hash table for complex.</maml:para>
        </maml:Description>
        <command:parameterValue required="true" variableLength="false">Hashtable</command:parameterValue>
        <dev:type>
          <maml:name>Hashtable</maml:name>
          <maml:uri />
        </dev:type>
        <dev:defaultValue>None</dev:defaultValue>
      </command:parameter>
    </command:parameters>
    <command:inputTypes>
      <command:inputType>
        <dev:type>
          <maml:name>System.Management.Automation.PSObject[]</maml:name>
        </dev:type>
        <maml:description>
          <maml:para></maml:para>
        </maml:description>
      </command:inputType>
    </command:inputTypes>
    <command:returnValues>
      <command:returnValue>
        <dev:type>
          <maml:name>System.Object</maml:name>
        </dev:type>
        <maml:description>
          <maml:para></maml:para>
        </maml:description>
      </command:returnValue>
    </command:returnValues>
    <maml:alertSet>
      <maml:alert>
        <maml:para>Learn more about PowerShell: http://jdhitsolutions.com/blog/essential-powershell-resources/</maml:para>
        <maml:para>Originally published at: http://jdhitsolutions.com/blog/powershell/3462/friday-fun-out-conditionalcolor/</maml:para>
      </maml:alert>
    </maml:alertSet>
    <command:examples>
      <command:example>
        <maml:title>Example 1</maml:title>
        <dev:code>PS C:\&gt; get-service -displayname windows* | out-conditionalcolor -propertyconditions @{Stopped='Red'} -property Status</dev:code>
        <dev:remarks>
          <maml:para>Get all services where the displayname starts with windows and display stopped services in red.</maml:para>
        </dev:remarks>
      </command:example>
      <command:example>
        <maml:title>Example 2</maml:title>
        <dev:code>PS C:\&gt; get-service -displayname windows* | out-conditionalcolor @{Stopped='Red'} status -ov winstop</dev:code>
        <dev:remarks>
          <maml:para>Repeat the previous example, but also save the output to the variable winstop. When you look at $Winstop you'll see the services, but they won't be coloredized. This example uses the parameters positionally.</maml:para>
        </dev:remarks>
      </command:example>
      <command:example>
        <maml:title>Example 3</maml:title>
        <dev:code>PS C:\&gt; get-eventlog system -newest 50 | out-conditionalcolor @{error='red';warning='yellow'}
Enter a property name: entrytype</dev:code>
        <dev:remarks>
          <maml:para>Get the newest 50 entries from the System event log. Display errors in red and warnings in yellow. If you don't specify a property you will be prompted.</maml:para>
        </dev:remarks>
      </command:example>
      <command:example>
        <maml:title>Example 4</maml:title>
        <dev:code>PS C:\&gt; $c =[ordered]@{{$psitem.length -ge 1mb}='red';{$psitem.length -ge 500KB}='yellow';{$psitem.length -ge 100KB}='cyan'}</dev:code>
        <dev:remarks>
          <maml:para>The first command creates an ordered hashtable based on the Length property.</maml:para>
        </dev:remarks>
      </command:example>
      <command:example>
        <maml:title>Example 5</maml:title>
        <dev:code>PS C:\&gt; dir c:\scripts\*.doc,c:\scripts\*.pdf,c:\scripts\*.xml |  out-conditionalcolor $c</dev:code>
        <dev:remarks>
          <maml:para>The next command uses it to get certain file types in the scripts folder and display the selected properties in color depending on the file size.</maml:para>
        </dev:remarks>
      </command:example>
    </command:examples>
    <command:relatedLinks>
      <maml:navigationLink>
        <maml:linkText>About_Hash_Tables</maml:linkText>
        <maml:uri></maml:uri>
      </maml:navigationLink>
    </command:relatedLinks>
  </command:command>
  <command:command xmlns:maml="http://schemas.microsoft.com/maml/2004/10" xmlns:command="http://schemas.microsoft.com/maml/dev/command/2004/10" xmlns:dev="http://schemas.microsoft.com/maml/dev/2004/10" xmlns:MSHelp="http://msdn.microsoft.com/mshelp">
    <command:details>
      <command:name>Out-VerboseTee</command:name>
      <command:verb>Out</command:verb>
      <command:noun>VerboseTee</command:noun>
      <maml:description>
        <maml:para>Write to Verbose stream and a file</maml:para>
      </maml:description>
    </command:details>
    <maml:description>
      <maml:para>This command is intended to let you see your verbose output and write the verbose messages to a log file. It will only work if the verbose pipeline is enabled, usually when your command is run with -Verbose. This function is designed to be used within your scripts and functions. You either have to hard code a file name or find some other way to define it in your function or control script. You could pass a value as a parameter or set it as a PSDefaultParameterValue.</maml:para>
      <maml:para>This command has an alias of Tee-Verbose.</maml:para>
      <maml:para>Begin {
  $log = New-RandomFilename -useTemp -extension log
  Write-Detail "Starting $($myinvocation.mycommand)" -Prefix begin | Tee-Verbose $log     
  Write-Detail "Logging verbose output to $log" -prefix begin | Tee-Verbose -append     
  Write-Detail "Initializing data array" -Prefix begin | Tee-Verbose $log -append     
  $data = @() 
  } #begin</maml:para>
      <maml:para>When the command is run with -Verbose you will see the verbose output and it will be saved to the specified log file.</maml:para>
    </maml:description>
    <command:syntax>
      <command:syntaxItem>
        <maml:name>Out-VerboseTee</maml:name>
        <command:parameter required="true" variableLength="true" globbing="false" pipelineInput="False" position="0" aliases="none">
          <maml:name>Path</maml:name>
          <maml:Description>
            <maml:para>The path for the output file.</maml:para>
          </maml:Description>
          <command:parameterValue required="true" variableLength="false">String</command:parameterValue>
          <dev:type>
            <maml:name>String</maml:name>
            <maml:uri />
          </dev:type>
          <dev:defaultValue>None</dev:defaultValue>
        </command:parameter>
        <command:parameter required="false" variableLength="true" globbing="false" pipelineInput="False" position="named" aliases="none">
          <maml:name>Append</maml:name>
          <maml:Description>
            <maml:para>Append to the specified text file.</maml:para>
          </maml:Description>
          <dev:type>
            <maml:name>SwitchParameter</maml:name>
            <maml:uri />
          </dev:type>
          <dev:defaultValue>False</dev:defaultValue>
        </command:parameter>
        <command:parameter required="false" variableLength="true" globbing="false" pipelineInput="False" position="named" aliases="none">
          <maml:name>Encoding</maml:name>
          <maml:Description>
            <maml:para>Specify a file encoding.</maml:para>
          </maml:Description>
          <command:parameterValue required="true" variableLength="false">Encoding</command:parameterValue>
          <dev:type>
            <maml:name>Encoding</maml:name>
            <maml:uri />
          </dev:type>
          <dev:defaultValue>None</dev:defaultValue>
        </command:parameter>
        <command:parameter required="true" variableLength="true" globbing="false" pipelineInput="True (ByValue)" position="named" aliases="none">
          <maml:name>Value</maml:name>
          <maml:Description>
            <maml:para>The message to be displayed as a verbose message and saved to the file.</maml:para>
          </maml:Description>
          <command:parameterValue required="true" variableLength="false">Object</command:parameterValue>
          <dev:type>
            <maml:name>Object</maml:name>
            <maml:uri />
          </dev:type>
          <dev:defaultValue>None</dev:defaultValue>
        </command:parameter>
      </command:syntaxItem>
    </command:syntax>
    <command:parameters>
      <command:parameter required="false" variableLength="true" globbing="false" pipelineInput="False" position="named" aliases="none">
        <maml:name>Append</maml:name>
        <maml:Description>
          <maml:para>Append to the specified text file.</maml:para>
        </maml:Description>
        <command:parameterValue required="false" variableLength="false">SwitchParameter</command:parameterValue>
        <dev:type>
          <maml:name>SwitchParameter</maml:name>
          <maml:uri />
        </dev:type>
        <dev:defaultValue>False</dev:defaultValue>
      </command:parameter>
      <command:parameter required="false" variableLength="true" globbing="false" pipelineInput="False" position="named" aliases="none">
        <maml:name>Encoding</maml:name>
        <maml:Description>
          <maml:para>Specify a file encoding.</maml:para>
        </maml:Description>
        <command:parameterValue required="true" variableLength="false">Encoding</command:parameterValue>
        <dev:type>
          <maml:name>Encoding</maml:name>
          <maml:uri />
        </dev:type>
        <dev:defaultValue>None</dev:defaultValue>
      </command:parameter>
      <command:parameter required="true" variableLength="true" globbing="false" pipelineInput="False" position="0" aliases="none">
        <maml:name>Path</maml:name>
        <maml:Description>
          <maml:para>The path for the output file.</maml:para>
        </maml:Description>
        <command:parameterValue required="true" variableLength="false">String</command:parameterValue>
        <dev:type>
          <maml:name>String</maml:name>
          <maml:uri />
        </dev:type>
        <dev:defaultValue>None</dev:defaultValue>
      </command:parameter>
      <command:parameter required="true" variableLength="true" globbing="false" pipelineInput="True (ByValue)" position="named" aliases="none">
        <maml:name>Value</maml:name>
        <maml:Description>
          <maml:para>The message to be displayed as a verbose message and saved to the file.</maml:para>
        </maml:Description>
        <command:parameterValue required="true" variableLength="false">Object</command:parameterValue>
        <dev:type>
          <maml:name>Object</maml:name>
          <maml:uri />
        </dev:type>
        <dev:defaultValue>None</dev:defaultValue>
      </command:parameter>
    </command:parameters>
    <command:inputTypes>
      <command:inputType>
        <dev:type>
          <maml:name>System.Object</maml:name>
        </dev:type>
        <maml:description>
          <maml:para></maml:para>
        </maml:description>
      </command:inputType>
    </command:inputTypes>
    <command:returnValues>
      <command:returnValue>
        <dev:type>
          <maml:name>System.Object</maml:name>
        </dev:type>
        <maml:description>
          <maml:para></maml:para>
        </maml:description>
      </command:returnValue>
    </command:returnValues>
    <maml:alertSet>
      <maml:alert>
        <maml:para>Learn more about PowerShell: http://jdhitsolutions.com/blog/essential-powershell-resources/</maml:para>
      </maml:alert>
    </maml:alertSet>
    <command:examples>
      <command:example>
        <maml:title>Example 1</maml:title>
        <dev:code>PS C:\&gt; $VerbosePreference= "continue"
PS C:\&gt; $log = New-CustomFileName ".\VerboseLog_%time.txt"
PS C:\&gt; Write-Detail "This is a verbose log test" | Out-VerboseTee -path $log
PS C:\&gt; Get-Content $log
11/29/2017 08:21:31:0704 [PROCESS] This is a verbose log test
PS C:\&gt; $verbosePreference = "silentlyContinue"</dev:code>
        <dev:remarks>
          <maml:para>Normally you would use this command inside a function or script, but you can run it from the console if you want to understand how it works.</maml:para>
        </dev:remarks>
      </command:example>
    </command:examples>
    <command:relatedLinks>
      <maml:navigationLink>
        <maml:linkText>Write-Verbose</maml:linkText>
        <maml:uri></maml:uri>
      </maml:navigationLink>
      <maml:navigationLink>
        <maml:linkText>Write-Detail</maml:linkText>
        <maml:uri></maml:uri>
      </maml:navigationLink>
    </command:relatedLinks>
  </command:command>
  <command:command xmlns:maml="http://schemas.microsoft.com/maml/2004/10" xmlns:command="http://schemas.microsoft.com/maml/dev/command/2004/10" xmlns:dev="http://schemas.microsoft.com/maml/dev/2004/10" xmlns:MSHelp="http://msdn.microsoft.com/mshelp">
    <command:details>
      <command:name>Write-Detail</command:name>
      <command:verb>Write</command:verb>
      <command:noun>Detail</command:noun>
      <maml:description>
        <maml:para>Write a detailed message string</maml:para>
      </maml:description>
    </command:details>
    <maml:description>
      <maml:para>This command is designed to be used within your functions and scripts to make it easier to write a detailed message that you can use as verbose output. The assumption is that you are using an advanced function with a Begin, Process and End scriptblocks. You can create a detailed message to indicate what part of the code is being executed. The output will include a full time stamp, although you can shorten it to be only a time string which includes a millisecond value.</maml:para>
      <maml:para>In a script you might use it like this:</maml:para>
      <maml:para>    Begin {
    Write-Detail "Starting $($myinvocation.mycommand)" -Prefix begin | Write-Verbose         
    $tabs = "`t" * $tab         
    Write-Detail "Using a tab of $tab" -Prefix begin | Write-Verbose     
    } #begin</maml:para>
      <maml:para>If you don't specify a prefix, it will default to PROCESS.</maml:para>
    </maml:description>
    <command:syntax>
      <command:syntaxItem>
        <maml:name>Write-Detail</maml:name>
        <command:parameter required="true" variableLength="true" globbing="false" pipelineInput="False" position="0" aliases="none">
          <maml:name>Message</maml:name>
          <maml:Description>
            <maml:para>The message to display after the time stamp and prefix.</maml:para>
          </maml:Description>
          <command:parameterValue required="true" variableLength="false">String</command:parameterValue>
          <dev:type>
            <maml:name>String</maml:name>
            <maml:uri />
          </dev:type>
          <dev:defaultValue>None</dev:defaultValue>
        </command:parameter>
        <command:parameter required="false" variableLength="true" globbing="false" pipelineInput="False" position="named" aliases="none">
          <maml:name>NoDate</maml:name>
          <maml:Description>
            <maml:para>Don't display the full date, only the time.</maml:para>
          </maml:Description>
          <dev:type>
            <maml:name>SwitchParameter</maml:name>
            <maml:uri />
          </dev:type>
          <dev:defaultValue>False</dev:defaultValue>
        </command:parameter>
        <command:parameter required="false" variableLength="true" globbing="false" pipelineInput="False" position="named" aliases="none">
          <maml:name>Prefix</maml:name>
          <maml:Description>
            <maml:para>Indicate whether you are in the BEGIN, PROCESS or END script block.</maml:para>
          </maml:Description>
          <command:parameterValueGroup>
            <command:parameterValue required="false" command:variableLength="false">BEGIN</command:parameterValue>
            <command:parameterValue required="false" command:variableLength="false">PROCESS</command:parameterValue>
            <command:parameterValue required="false" command:variableLength="false">END</command:parameterValue>
          </command:parameterValueGroup>
          <command:parameterValue required="true" variableLength="false">String</command:parameterValue>
          <dev:type>
            <maml:name>String</maml:name>
            <maml:uri />
          </dev:type>
          <dev:defaultValue>PROCESS</dev:defaultValue>
        </command:parameter>
      </command:syntaxItem>
    </command:syntax>
    <command:parameters>
      <command:parameter required="true" variableLength="true" globbing="false" pipelineInput="False" position="0" aliases="none">
        <maml:name>Message</maml:name>
        <maml:Description>
          <maml:para>The message to display after the time stamp and prefix.</maml:para>
        </maml:Description>
        <command:parameterValue required="true" variableLength="false">String</command:parameterValue>
        <dev:type>
          <maml:name>String</maml:name>
          <maml:uri />
        </dev:type>
        <dev:defaultValue>None</dev:defaultValue>
      </command:parameter>
      <command:parameter required="false" variableLength="true" globbing="false" pipelineInput="False" position="named" aliases="none">
        <maml:name>NoDate</maml:name>
        <maml:Description>
          <maml:para>Don't display the full date, only the time.</maml:para>
        </maml:Description>
        <command:parameterValue required="false" variableLength="false">SwitchParameter</command:parameterValue>
        <dev:type>
          <maml:name>SwitchParameter</maml:name>
          <maml:uri />
        </dev:type>
        <dev:defaultValue>False</dev:defaultValue>
      </command:parameter>
      <command:parameter required="false" variableLength="true" globbing="false" pipelineInput="False" position="named" aliases="none">
        <maml:name>Prefix</maml:name>
        <maml:Description>
          <maml:para>Indicate whether you are in the BEGIN, PROCESS or END script block.</maml:para>
        </maml:Description>
        <command:parameterValue required="true" variableLength="false">String</command:parameterValue>
        <dev:type>
          <maml:name>String</maml:name>
          <maml:uri />
        </dev:type>
        <dev:defaultValue>PROCESS</dev:defaultValue>
      </command:parameter>
    </command:parameters>
    <command:inputTypes>
      <command:inputType>
        <dev:type>
          <maml:name>None</maml:name>
        </dev:type>
        <maml:description>
          <maml:para></maml:para>
        </maml:description>
      </command:inputType>
    </command:inputTypes>
    <command:returnValues>
      <command:returnValue>
        <dev:type>
          <maml:name>System.String</maml:name>
        </dev:type>
        <maml:description>
          <maml:para></maml:para>
        </maml:description>
      </command:returnValue>
    </command:returnValues>
    <maml:alertSet>
      <maml:alert>
        <maml:para>Learn more about PowerShell: http://jdhitsolutions.com/blog/essential-powershell-resources/</maml:para>
      </maml:alert>
    </maml:alertSet>
    <command:examples>
      <command:example>
        <maml:title>Example 1</maml:title>
        <dev:code>PS C:\&gt;write-detail "Getting file information" -Prefix Process -NoDate
02:39:18:4874 [PROCESS] Getting file information</dev:code>
        <dev:remarks>
          <maml:para>Normally you would use this command in a function, but here is an example from the console so that you can see what to expect.</maml:para>
        </dev:remarks>
      </command:example>
    </command:examples>
    <command:relatedLinks>
      <maml:navigationLink>
        <maml:linkText>Write-Verbose</maml:linkText>
        <maml:uri></maml:uri>
      </maml:navigationLink>
    </command:relatedLinks>
  </command:command>
</helpItems>